pytpm2.cpython-35m-x86_64-linux-gnu.so
pytpm2-0.0.2.dist-info/top_level.txt
pytpm2-0.0.2.dist-info/WHEEL
pytpm2-0.0.2.dist-info/METADATA
pytpm2-0.0.2.dist-info/RECORD
.libspytpm2/libtss2-sys-d8a2214d.so.0.0.0
.libspytpm2/libtss2-mu-ab632384.so.0.0.0
.libspytpm2/libcrypto-3feaf255.so.1.0.0
.libspytpm2/libtss2-esys-3931c8df.so.0.0.0
